{"cameraMode":{"drawMode":0,"name":"Shaded","section":"Shading Mode"},"sceneLighting":false,"audioPlay":false,"sceneViewState":{"m_AlwaysRefresh":true,"showFog":true,"showSkybox":false,"showFlares":true,"showImageEffects":true,"showParticleSystems":true,"showVisualEffectGraphs":true,"m_FxEnabled":true},"in2DMode":false,"pivot":{"x":23.145584106445314,"y":6.1210174560546879,"z":-38.49999237060547},"rotation":{"x":0.2916894853115082,"y":0.5932231545448303,"z":-0.24385058879852296,"w":0.7096192836761475},"size":28.56607437133789,"orthographic":false}