{"cameraMode":{"drawMode":0,"name":"Shaded","section":"Shading Mode"},"sceneLighting":false,"audioPlay":false,"sceneViewState":{"m_AlwaysRefresh":true,"showFog":true,"showSkybox":false,"showFlares":true,"showImageEffects":true,"showParticleSystems":true,"showVisualEffectGraphs":true,"m_FxEnabled":true},"in2DMode":false,"pivot":{"x":0.0,"y":0.5567517280578613,"z":2.9802322387695315e-8},"rotation":{"x":0.2208525538444519,"y":0.743495523929596,"z":-0.2939552664756775,"w":0.5586381554603577},"size":1.112892508506775,"orthographic":false}